gretl4py-0.31.dist-info/RECORD
gretl4py-0.31.dist-info/WHEEL
gretl4py-0.31.dist-info/top_level.txt
gretl4py-0.31.dist-info/METADATA
gretl4py-0.31.dist-info/licenses/LICENSE
gretl/_gretl.cpython-314-darwin.so
gretl/gretl4py_addons.py
gretl/gretl4py_classes.py
gretl/__init__.py
gretl/.dylibs/libpango-1.0.0.dylib
gretl/.dylibs/libffi.8.dylib
gretl/.dylibs/libgsf-1.114.dylib
gretl/.dylibs/libgtk-3.0.dylib
gretl/.dylibs/libpcre2-8.0.dylib
gretl/.dylibs/libcairo.2.dylib
gretl/.dylibs/libcairo-gobject.2.dylib
gretl/.dylibs/libglib-2.0.0.dylib
gretl/.dylibs/libgdk_pixbuf-2.0.0.dylib
gretl/.dylibs/libpng16.16.dylib
gretl/.dylibs/libjson-glib-1.0.0.dylib
gretl/.dylibs/libepoxy.0.dylib
gretl/.dylibs/libpangocairo-1.0.0.dylib
gretl/.dylibs/libomp.dylib
gretl/.dylibs/libgobject-2.0.0.dylib
gretl/.dylibs/libpixman-1.0.40.0.dylib
gretl/.dylibs/libharfbuzz.0.dylib
gretl/.dylibs/libgmodule-2.0.0.dylib
gretl/.dylibs/libintl.8.dylib
gretl/.dylibs/libatk-1.0.0.dylib
gretl/.dylibs/libfribidi.0.dylib
gretl/.dylibs/liblpsolve55.dylib
gretl/.dylibs/libcurl.4.dylib
gretl/.dylibs/libgretl-1.0.52.dylib
gretl/.dylibs/libfftw3.3.dylib
gretl/.dylibs/libgdk-3.0.dylib
gretl/.dylibs/libgmp.10.dylib
gretl/.dylibs/libmpfr.6.dylib
gretl/.dylibs/libgio-2.0.0.dylib
gretl/examples/__init__.py
gretl/examples/data_management/nparray2dict.py
gretl/examples/data_management/series2dict.py
gretl/examples/data_management/df2dict.py
gretl/examples/data_management/sample.py
gretl/examples/data_management/longley.csv
gretl/examples/module_related_tools/set.py
gretl/examples/estimators/negbin.py
gretl/examples/estimators/logit.py
gretl/examples/estimators/lad.py
gretl/examples/estimators/poisson.py
gretl/examples/estimators/logistic.py
gretl/examples/estimators/ols.py
gretl/examples/estimators/duration.py
gretl/examples/estimators/wls.py
gretl/examples/estimators/tsls.py
gretl/examples/estimators/tobit.py
gretl/examples/estimators/ar.py
gretl/examples/estimators/probit.py
gretl/examples/estimators/biprobit.py
gretl/examples/estimators/panel.py
gretl/examples/estimators/garch.py
gretl/examples/estimators/quantreg.py
