Metadata-Version: 2.4
Name: gretl4py
Version: 0.31
Summary: Python bindings for gretl
Author: Marcin Błażejowski
Author-email: Marcin Błażejowski <marcin@gretlconference.org>
License-Expression: GPL-3.0-or-later
Project-URL: Documentation, https://gretl.sourceforge.net/gretl4py.html
Classifier: Programming Language :: Python :: 3
Classifier: Programming Language :: C++
Classifier: Operating System :: OS Independent
Classifier: Development Status :: 4 - Beta
Classifier: Intended Audience :: Developers
Classifier: Topic :: Scientific/Engineering
Requires-Python: >=3.11
License-File: LICENSE
Requires-Dist: numpy>=1.22
Dynamic: author
Dynamic: license-file
Dynamic: requires-python
